aioipfs/__init__.py
aioipfs/__main__.py
aioipfs/api.py
aioipfs/exceptions.py
aioipfs/find.py
aioipfs/gitignore_parser.py
aioipfs/helpers.py
aioipfs/multi.py
aioipfs/apis/__init__.py
aioipfs/apis/pin.py
privex_aioipfs-0.5.8.data/scripts/ipfs-find
privex_aioipfs-0.5.8.dist-info/LICENSE
privex_aioipfs-0.5.8.dist-info/METADATA
privex_aioipfs-0.5.8.dist-info/WHEEL
privex_aioipfs-0.5.8.dist-info/top_level.txt
privex_aioipfs-0.5.8.dist-info/RECORD
