Metadata-Version: 2.1
Name: privex-aioipfs
Version: 0.5.8
Summary: Asynchronous IPFS client library (Privex Fork)
Home-page: https://github.com/Privex/aioipfs
Author: cipres
Author-email: chris@privex.io
License: LGPLv3
Keywords: asyncio,aiohttp,ipfs
Platform: UNKNOWN
Classifier: Programming Language :: Python
Classifier: Programming Language :: Python :: 3.6
Classifier: Programming Language :: Python :: 3.7
Classifier: Intended Audience :: Developers
Classifier: Development Status :: 4 - Beta
Classifier: Natural Language :: English
Classifier: Operating System :: OS Independent
Classifier: License :: OSI Approved :: GNU Lesser General Public License v3 (LGPLv3)
Classifier: Topic :: System :: Filesystems
Requires-Dist: aiohttp (>=3.7.4)
Requires-Dist: aiofiles (>=0.4.0)
Requires-Dist: base58 (>=1.0.2)
Requires-Dist: orjson (>=3.4)
